peerpy/__init__.py
peerpy/connection.py
peerpy/data.py
peerpy/event_handler.py
peerpy/exceptions.py
peerpy/peer.py
peerpy/protocol.py
peerpy/utils/__init__.py
tests/__init__.py
tests/conftest.py
tests/utils.py
tests/connection/__init__.py
tests/connection/conftest.py
tests/connection/test_handlers.py
tests/connection/test_receive.py
tests/connection/test_send.py
tests/peer/__init__.py
tests/peer/test_connect.py
tests/peer/test_errors.py
tests/peer/test_handlers.py
tests/peer/test_pinger.py
tests/peer/test_properties.py
tests/peer/test_statements.py
peerpy-1.2.2.dist-info/LICENSE
peerpy-1.2.2.dist-info/METADATA
peerpy-1.2.2.dist-info/WHEEL
peerpy-1.2.2.dist-info/top_level.txt
peerpy-1.2.2.dist-info/RECORD
