Metadata-Version: 2.1
Name: peerpy
Version: 1.2.2
Summary: p2p connection over TCP made dead simple!
Home-page: https://github.com/Rubilmax/peerpy
Author: Rubilmax
Author-email: rmilon@gmail.com
License: UNKNOWN
Platform: UNKNOWN
Classifier: Programming Language :: Python :: 3
Classifier: License :: OSI Approved :: MIT License
Classifier: Operating System :: OS Independent
Requires-Python: >=3.6
